Metadata-Version: 2.1
Name: handyfiles
Version: 0.0.1
Summary: A comprehensive file utility package
Author: Butare
Classifier: Programming Language :: Python :: 3
Classifier: License :: OSI Approved :: MIT License
Classifier: Operating System :: OS Independent
Requires-Python: >=3.6
License-File: LICENSE
